Slame/__init__.py
Slame/slame.py
Slame/utils.py
Slame-1.6.3.dist-info/METADATA
Slame-1.6.3.dist-info/WHEEL
Slame-1.6.3.dist-info/top_level.txt
Slame-1.6.3.dist-info/RECORD
